setup.py
ahmetturk_probability/Binomialdistribution.py
ahmetturk_probability/Gaussiandistribution.py
ahmetturk_probability/Generaldistribution.py
ahmetturk_probability/__init__.py
ahmetturk_probability.egg-info/PKG-INFO
ahmetturk_probability.egg-info/SOURCES.txt
ahmetturk_probability.egg-info/dependency_links.txt
ahmetturk_probability.egg-info/not-zip-safe
ahmetturk_probability.egg-info/top_level.txt