Metadata-Version: 2.1
Name: ahmetturk-probability
Version: 1.0
Summary: Gaussian and Binomial distributions
Author: Ahmet Türk
